lecture_downloader/__init__.py
lecture_downloader/cli.py
lecture_downloader/completion.py
lecture_downloader/downloader.py
lecture_downloader/merger.py
lecture_downloader/pipeline.py
lecture_downloader/processor.py
lecture_downloader/transcriber.py
lecture_downloader/utils.py
lecture_downloader-1.1.13.dist-info/licenses/LICENSE
lecture_downloader-1.1.13.dist-info/METADATA
lecture_downloader-1.1.13.dist-info/WHEEL
lecture_downloader-1.1.13.dist-info/entry_points.txt
lecture_downloader-1.1.13.dist-info/top_level.txt
lecture_downloader-1.1.13.dist-info/RECORD
